oafuncs/__init__.py
oafuncs/oa_cmap.py
oafuncs/oa_data.py
oafuncs/oa_date.py
oafuncs/oa_draw.py
oafuncs/oa_file.py
oafuncs/oa_geo.py
oafuncs/oa_help.py
oafuncs/oa_linux.py
oafuncs/oa_nc.py
oafuncs/oa_python.py
oafuncs/oa_tool.py
oafuncs/_data/hycom.png
oafuncs/_data/oafuncs.png
oafuncs/_script/cprogressbar.py
oafuncs/_script/data_interp.py
oafuncs/_script/email.py
oafuncs/_script/netcdf_merge.py
oafuncs/_script/netcdf_modify.py
oafuncs/_script/netcdf_write.py
oafuncs/_script/parallel.py
oafuncs/_script/parallel_bak.py
oafuncs/_script/plot_dataset.py
oafuncs/_script/process_roms.py
oafuncs/_script/replace_file_content.py
oafuncs/oa_down/User_Agent-list.txt
oafuncs/oa_down/__init__.py
oafuncs/oa_down/hycom_3hourly.py
oafuncs/oa_down/idm.py
oafuncs/oa_down/literature.py
oafuncs/oa_down/read_proxy.py
oafuncs/oa_down/test_ua.py
oafuncs/oa_down/user_agent.py
oafuncs/oa_model/__init__.py
oafuncs/oa_model/roms.py
oafuncs/oa_model/wrf/__init__.py
oafuncs/oa_model/wrf/little_r.py
oafuncs/oa_sign/__init__.py
oafuncs/oa_sign/meteorological.py
oafuncs/oa_sign/ocean.py
oafuncs/oa_sign/scientific.py
oafuncs-0.0.98.60.dist-info/licenses/LICENSE.txt
oafuncs-0.0.98.60.dist-info/METADATA
oafuncs-0.0.98.60.dist-info/WHEEL
oafuncs-0.0.98.60.dist-info/top_level.txt
oafuncs-0.0.98.60.dist-info/RECORD
