Metadata-Version: 2.4
Name: oafuncs
Version: 0.0.98.60
Summary: Oceanic and Atmospheric Functions
Home-page: https://github.com/Industry-Pays/OAFuncs
Author: Kun Liu
Author-email: liukun0312@stu.ouc.edu.cn
License: MIT
Classifier: License :: OSI Approved :: MIT License
Classifier: Programming Language :: Python
Classifier: Programming Language :: Python :: 3
Classifier: Programming Language :: Python :: 3.10
Classifier: Programming Language :: Python :: 3.11
Classifier: Programming Language :: Python :: 3.12
Classifier: Programming Language :: Python :: 3.13
Classifier: Programming Language :: Python :: Implementation :: CPython
Classifier: Programming Language :: Python :: Implementation :: PyPy
Requires-Python: >=3.10.0
License-File: LICENSE.txt
Requires-Dist: numpy
Requires-Dist: scipy
Requires-Dist: pandas
Requires-Dist: xarray
Requires-Dist: rich
Requires-Dist: pathlib
Requires-Dist: lxml
Requires-Dist: requests
Requires-Dist: bs4
Requires-Dist: httpx
Requires-Dist: matplotlib
Requires-Dist: opencv-python
Requires-Dist: netCDF4
Requires-Dist: xlrd
Requires-Dist: geopandas
Requires-Dist: Cartopy
Requires-Dist: rasterio
Requires-Dist: salem
Requires-Dist: psutil
Requires-Dist: dask
Dynamic: author
Dynamic: author-email
Dynamic: classifier
Dynamic: description
Dynamic: description-content-type
Dynamic: home-page
Dynamic: license
Dynamic: license-file
Dynamic: requires-dist
Dynamic: requires-python
Dynamic: summary
